.coveragerc
.hgignore
.hgtags
CHANGES.txt
COPYRIGHT.txt
HACKING.txt
LICENSE.txt
README.txt
setup.py
src/buildout/__init__.py
src/buildout.disablessl.egg-info/PKG-INFO
src/buildout.disablessl.egg-info/SOURCES.txt
src/buildout.disablessl.egg-info/dependency_links.txt
src/buildout.disablessl.egg-info/entry_points.txt
src/buildout.disablessl.egg-info/namespace_packages.txt
src/buildout.disablessl.egg-info/not-zip-safe
src/buildout.disablessl.egg-info/requires.txt
src/buildout.disablessl.egg-info/top_level.txt
src/buildout/disablessl/__init__.py