Metadata-Version: 1.0
Name: buildout.disablessl
Version: 1.1
Summary: Disable SSL verification of setuptools for buildout
Home-page: https://bitbucket.org/gocept/buildout.disablessl/
Author: gocept <mail@gocept.com>
Author-email: mail@gocept.com
License: ZPL 2.1
Platform: UNKNOWN
